{
  "timestamp": "2026-02-09 22:23:43",
  "mode": "LIVE",
  "route": {
    "from": "HBAR",
    "to": "USDC",
    "steps": 1,
    "total_cost_hbar": 1.6611990863116446,
    "hashpack_visible": true
  },
  "amount_token": 1.0,
  "amount_usd": 0.09,
  "gas_used": 187278,
  "results": [
    {
      "success": true,
      "tx_hash": "990f606dc8f241141f8cca7028273bb094602832581b4badabd17124cf868118",
      "gas_used": 187278,
      "error": "",
      "block_number": 90963665,
      "timestamp": "2026-02-09 22:23:36",
      "steps_completed": 0,
      "total_steps": 0
    }
  ],
  "success": true,
  "account": "0x76D2580A07Eebaa790a286df2BD1f8b13655C5fa",
  "network": "mainnet"
}